rellm/__init__.py
rellm/logits_mask.py
rellm/re_token_filter.py
rellm/rellm.py
rellm-0.0.5.dist-info/LICENSE
rellm-0.0.5.dist-info/WHEEL
rellm-0.0.5.dist-info/METADATA
rellm-0.0.5.dist-info/RECORD
