Metadata-Version: 2.1
Name: rellm
Version: 0.0.5
Summary: Get exact structure out of any language models with regular expressions.
License: MIT
Keywords: llm,ai,prompt,large language models,gpt-3,chatgpt
Author: Matt Rickard
Author-email: pypi@matt-rickard.com
Maintainer: Matt Rickard
Maintainer-email: pypi@matt-rickard.com
Requires-Python: >=3.8,<4.0
Classifier: Development Status :: 3 - Alpha
Classifier: Intended Audience :: Developers
Classifier: Intended Audience :: Science/Research
Classifier: License :: OSI Approved :: MIT License
Classifier: Programming Language :: Python :: 3
Classifier: Programming Language :: Python :: 3.8
Classifier: Programming Language :: Python :: 3.9
Classifier: Programming Language :: Python :: 3.10
Classifier: Programming Language :: Python :: 3.11
Classifier: Programming Language :: Python :: 3
Classifier: Programming Language :: Python :: 3 :: Only
Classifier: Programming Language :: Python :: 3.7
Classifier: Programming Language :: Python :: 3.8
Classifier: Programming Language :: Python :: 3.9
Classifier: Topic :: Scientific/Engineering :: Artificial Intelligence
Classifier: Topic :: Software Development :: Libraries :: Python Modules
Classifier: Topic :: Text Processing :: Linguistic
Requires-Dist: numpy (>=1.24.3,<2.0.0)
Requires-Dist: regex (>=2023.5.5,<2024.0.0)
Requires-Dist: torch (>=2.0.0,<3.0.0)
Requires-Dist: transformers (>=4.28.1,<5.0.0)
Project-URL: repository, https://github.com/r2d4/rellm
